<?xml version="1.0" encoding="UTF-8" standalone="no"?>
<list grade="D">
	<items type="Heavy">
		<item id="58"/><!-- Мифриловая Кираса -->
		<item id="59"/><!-- Мифриловые Набедренники -->
		<item id="47"/><!-- Шлем -->
		<item id="628"/><!-- Хоплон -->
	</items>
	<items type="Heavy">
		<item id="352"/><!-- Панцирная Туника -->
		<item id="2378"/><!-- Панцирные Набедренники -->
		<item id="2411"/><!-- Панцирный Шлем -->
		<item id="2493"/><!-- Панцирный Щит -->
	</items>

	<items type="Light">
		<item id="394"/><!-- Укрепленная Кожаная Рубаха -->
		<item id="416"/><!-- Укрепленные Кожаные Набедренники -->
		<item id="2422"/><!-- Укрепленные Кожаные Сапоги -->
	</items>
	<items type="Light">
		<item id="395"/><!-- Рубаха из Шкуры Мантикоры -->
		<item id="417"/><!-- Набедренники из Шкуры Мантикоры -->
		<item id="2424"/><!-- Сапоги из Шкуры Мантикоры -->
	</items>

	<items type="Magic">
		<item id="436"/><!-- Туника Знаний -->
		<item id="469"/><!-- Штаны Знаний -->
		<item id="2447"/><!-- Перчатки Знаний -->
	</items>
	<items type="Magic">
		<item id="437"/><!-- Мифриловая Туника -->
		<item id="470"/><!-- Мифриловые Штаны -->
		<item id="2450"/><!-- Мифриловые Перчатки Эльфов -->
	</items>
</list>